Simis/Ashes.py
Simis/TcpConnector.py
Simis/__init__.py
Simis/datastore.py
Simis-2.1.0.dist-info/METADATA
Simis-2.1.0.dist-info/WHEEL
Simis-2.1.0.dist-info/top_level.txt
Simis-2.1.0.dist-info/RECORD
