Metadata-Version: 2.1
Name: Simis
Version: 2.1.0
Summary: A package for communicating with the Ashes wind turbine simulation software in order to run custom simulation code.
Home-page: https://www.simis.io
Author: Simis AS
Author-email: support@simis.io
Classifier: Development Status :: 3 - Alpha
Classifier: Programming Language :: Python :: 3
Classifier: License :: Other/Proprietary License
Classifier: Operating System :: Microsoft :: Windows
Requires-Dist: PySide6
